scipeds/__init__.py
scipeds/cli.py
scipeds/constants.py
scipeds/utils.py
scipeds/data/__init__.py
scipeds/data/completions.py
scipeds/data/engine.py
scipeds/data/enums.py
scipeds/data/queries.py
scipeds/data/tests/test_calculations.py
scipeds/data/tests/test_constants.py
scipeds/data/tests/test_models.py
scipeds/data/tests/test_queries.py
scipeds/data/tests/assets/test.duckdb
scipeds/tests/test_transforms.py
scipeds-0.0.8.dist-info/entry_points.txt
scipeds-0.0.8.dist-info/licenses/LICENSE
scipeds-0.0.8.dist-info/WHEEL
scipeds-0.0.8.dist-info/METADATA
scipeds-0.0.8.dist-info/RECORD
