Metadata-Version: 2.4
Name: scipeds
Version: 0.0.8
Summary: A Python package for working with IPEDS data
Author-email: Science for America <info@scienceforamerica.org>, DrivenData <info@drivendata.org>
Requires-Python: >=3.10
Classifier: Development Status :: 4 - Beta
Classifier: Intended Audience :: Science/Research
Classifier: License :: OSI Approved :: MIT License
Classifier: Programming Language :: Python :: 3
Classifier: Programming Language :: Python :: 3.10
Classifier: Programming Language :: Python :: 3.11
Classifier: Programming Language :: Python :: 3.12
Classifier: Programming Language :: Python :: 3.13
Classifier: Topic :: Education
License-File: LICENSE
Requires-Dist: cloudpathlib[gs]
Requires-Dist: duckdb
Requires-Dist: google-cloud-storage
Requires-Dist: numpy
Requires-Dist: pandas
Requires-Dist: platformdirs
Requires-Dist: pydantic
Requires-Dist: statsmodels
Requires-Dist: typer
Project-URL: Changelog, https://github.com/scienceforamerica/scipeds/blob/main/HISTORY.md
Project-URL: Documentation, https://docs.scipeds.org
Project-URL: Issues, https://github.com/scienceforamerica/scipeds/issues
Project-URL: Repository, https://github.com/scienceforamerica/scipeds.git
